hello_whitecapella/__init__.py
hello_whitecapella/hello.py
hello_WhiteCapella-0.7.0.dist-info/METADATA
hello_WhiteCapella-0.7.0.dist-info/WHEEL
hello_WhiteCapella-0.7.0.dist-info/entry_points.txt
hello_WhiteCapella-0.7.0.dist-info/top_level.txt
hello_WhiteCapella-0.7.0.dist-info/RECORD
