Metadata-Version: 2.1
Name: hello_WhiteCapella
Version: 0.7.0
Summary: Default template for PDM package
Author-email: WhiteCapella1 <whitecapella@naver.com>
License: MIT
Requires-Python: ==3.12.*
